pymapadmin/__about__.py
pymapadmin/__init__.py
pymapadmin/config.py
pymapadmin/local.py
pymapadmin/main.py
pymapadmin/operation.py
pymapadmin/py.typed
pymapadmin/typing.py
pymapadmin/commands/__init__.py
pymapadmin/commands/base.py
pymapadmin/commands/health.py
pymapadmin/commands/mailbox.py
pymapadmin/commands/system.py
pymapadmin/commands/user.py
pymapadmin/grpc/__init__.py
pymapadmin/grpc/admin.proto
pymapadmin/grpc/admin_grpc.py
pymapadmin/grpc/admin_pb2.py
pymapadmin/grpc/admin_pb2.pyi
pymapadmin/grpc/error_details.proto
pymapadmin/grpc/error_details_grpc.py
pymapadmin/grpc/error_details_pb2.py
pymapadmin/grpc/error_details_pb2.pyi
pymapadmin/grpc/grpc_tools.protoc-args
pymapadmin/grpc/health.proto
pymapadmin/grpc/health_grpc.py
pymapadmin/grpc/health_pb2.py
pymapadmin/grpc/health_pb2.pyi
pymap_admin-0.12.1.dist-info/METADATA
pymap_admin-0.12.1.dist-info/WHEEL
pymap_admin-0.12.1.dist-info/entry_points.txt
pymap_admin-0.12.1.dist-info/licenses/LICENSE.md
pymap_admin-0.12.1.dist-info/RECORD
