Metadata-Version: 2.1
Name: pymap-admin
Version: 0.12.1
Summary: Tool for administering running pymap instances.
Project-URL: Homepage, https://github.com/icgood/pymap-admin/
Project-URL: API Documentation, https://icgood.github.io/pymap-admin/
Author-email: Ian Good <ian@icgood.net>
License: ## The MIT License (MIT)
License-File: LICENSE.md
Classifier: Development Status :: 3 - Alpha
Classifier: Intended Audience :: Developers
Classifier: Intended Audience :: Information Technology
Classifier: License :: OSI Approved :: MIT License
Classifier: Programming Language :: Python
Classifier: Programming Language :: Python :: 3.11
Classifier: Topic :: Communications :: Email :: Post-Office
Classifier: Topic :: Communications :: Email :: Post-Office :: IMAP
Requires-Python: ~=3.11
Requires-Dist: grpclib~=0.4
Requires-Dist: protobuf~=4.23
Requires-Dist: typing-extensions
Provides-Extra: build
Requires-Dist: grpcio-tools; extra == 'build'
Requires-Dist: mypy-protobuf; extra == 'build'
